{"title": "Focaccia Charcuterie Board", "selftext": "", "url": "https://v.redd.it/jjf1u4pf0jl71", "created_utc": 1630778576.0, "score": 25, "author": "CableStoned", "num_comments": 0, "permalink": "/r/FoodPornGifs/comments/phwflo/focaccia_charcuterie_board/", "html_title": "Reddit - The heart of the internet"}
{"title": "Ignore my dirty oven please", "selftext": "", "url": "https://v.redd.it/eoyrg8wt23v41", "created_utc": 1587872560.0, "score": 22, "author": "KittyNouveau", "num_comments": 1, "permalink": "/r/FoodPornGifs/comments/g87ges/ignore_my_dirty_oven_please/", "html_title": "Reddit - The heart of the internet"}
{"title": "Dessert from \"Chop\" at the Venetian", "selftext": "", "url": "https://v.redd.it/h3ocjbfj3or61", "created_utc": 1617764735.0, "score": 20, "author": "Yubenbroken", "num_comments": 1, "permalink": "/r/FoodPornGifs/comments/mlstg8/dessert_from_chop_at_the_venetian/", "html_title": "Reddit - The heart of the internet"}
{"title": "Unacceptable", "selftext": "", "url": "https://i.redd.it/3acuole8bwx31.jpg", "created_utc": 1573407647.0, "score": 17, "author": "howthefuge6", "num_comments": 1, "permalink": "/r/FoodPornGifs/comments/dueil1/unacceptable/", "html_title": ""}
{"title": "Homemade", "selftext": "", "url": "https://v.redd.it/pgxxt04etip21", "created_utc": 1554066986.0, "score": 16, "author": "None", "num_comments": 0, "permalink": "/r/FoodPornGifs/comments/b7svo1/homemade/", "html_title": "Reddit - The heart of the internet"}
{"title": "Filet in a frying pan", "selftext": "", "url": "http://i.imgur.com/tZ8gZxn.gif", "created_utc": 1401472548.0, "score": 16, "author": "holdenwook", "num_comments": 1, "permalink": "/r/FoodPornGifs/comments/26w4mm/filet_in_a_frying_pan/", "html_title": ""}
{"title": "Egg porn over a open faced steak sandwich.", "selftext": "", "url": "https://v.redd.it/g7ml724hyes41", "created_utc": 1586708892.0, "score": 15, "author": "1578W", "num_comments": 0, "permalink": "/r/FoodPornGifs/comments/fzzrcz/egg_porn_over_a_open_faced_steak_sandwich/", "html_title": "Reddit - The heart of the internet"}
{"title": "Waffle Porn. Crispy on the outside, Fluffy on the inside :) - Recipe in comment.", "selftext": "", "url": "https://gfycat.com/wideeyedamazinghectorsdolphin", "created_utc": 1594618695.0, "score": 12, "author": "mahcyen", "num_comments": 1, "permalink": "/r/FoodPornGifs/comments/hq9o0g/waffle_porn_crispy_on_the_outside_fluffy_on_the/", "html_title": ""}
{"title": "Homemade Boba milk tea", "selftext": "", "url": "https://v.redd.it/wporcujmeo561", "created_utc": 1608179784.0, "score": 11, "author": "sturdybison74", "num_comments": 0, "permalink": "/r/FoodPornGifs/comments/keqf32/homemade_boba_milk_tea/", "html_title": "Reddit - The heart of the internet"}
{"title": "Steak&Eggs", "selftext": "", "url": "https://v.redd.it/8yswxaou7h561", "created_utc": 1608092769.0, "score": 11, "author": "Whitebread_92", "num_comments": 0, "permalink": "/r/FoodPornGifs/comments/ke28ir/steakeggs/", "html_title": "Reddit - The heart of the internet"}
{"title": "Tomahawk steak on chimney grill", "selftext": "", "url": "https://v.redd.it/2hls88x1gbz41", "created_utc": 1589717294.0, "score": 12, "author": "wanton85", "num_comments": 1, "permalink": "/r/FoodPornGifs/comments/glebkw/tomahawk_steak_on_chimney_grill/", "html_title": "Reddit - The heart of the internet"}
{"title": "Castella Sponge Cake [xpost r/oddlysatisfying]", "selftext": "", "url": "http://i.imgur.com/0J7CWZr.gifv", "created_utc": 1455678583.0, "score": 10, "author": "Hashbrown777", "num_comments": 2, "permalink": "/r/FoodPornGifs/comments/4667nc/castella_sponge_cake_xpost_roddlysatisfying/", "html_title": ""}
{"title": "A Delectable Dessert.", "selftext": "", "url": "http://gfycat.com/CloseWellinformedChimpanzee", "created_utc": 1407982323.0, "score": 11, "author": "Motha_Effin_Kitty_Yo", "num_comments": 0, "permalink": "/r/FoodPornGifs/comments/2dhzhw/a_delectable_dessert/", "html_title": ""}
{"title": "its sushi time - art by me", "selftext": "", "url": "https://i.redd.it/qycimuhr29c51.gif", "created_utc": 1595354599.0, "score": 10, "author": "mangadrawing123", "num_comments": 1, "permalink": "/r/FoodPornGifs/comments/hvcd4b/its_sushi_time_art_by_me/", "html_title": ""}
{"title": "Tearing into a pizza.", "selftext": "", "url": "http://i.imgur.com/7siGit8.gif", "created_utc": 1410646525.0, "score": 9, "author": "Motha_Effin_Kitty_Yo", "num_comments": 2, "permalink": "/r/FoodPornGifs/comments/2gbmsq/tearing_into_a_pizza/", "html_title": ""}
{"title": "Pizza! I don't even eat cheese pizza, but damn, this makes me want to.", "selftext": "", "url": "http://imgur.com/xRMDCkV", "created_utc": 1407824820.0, "score": 9, "author": "asifsys23", "num_comments": 0, "permalink": "/r/FoodPornGifs/comments/2dbb1s/pizza_i_dont_even_eat_cheese_pizza_but_damn_this/", "html_title": ""}
{"title": "Blue food porn \ud83d\udc99", "selftext": "", "url": "https://v.redd.it/pmvn73d7emw91", "created_utc": 1666994911.0, "score": 7, "author": "Stinkylilsockies", "num_comments": 0, "permalink": "/r/FoodPornGifs/comments/yg21gd/blue_food_porn/", "html_title": "Reddit - The heart of the internet"}
{"title": "Chocolate Mousse", "selftext": "", "url": "http://24.media.tumblr.com/tumblr_mdv23l2fqs1rzko2no1_500.gif", "created_utc": 1430997970.0, "score": 6, "author": "Oddslat", "num_comments": 0, "permalink": "/r/FoodPornGifs/comments/355xk4/chocolate_mousse/", "html_title": ""}
{"title": "Baileys Ganache on sweet potato brownies", "selftext": "", "url": "https://gfycat.com/tidypracticalheron", "created_utc": 1563530653.0, "score": 6, "author": "pixxelzombie", "num_comments": 1, "permalink": "/r/FoodPornGifs/comments/cf5oyf/baileys_ganache_on_sweet_potato_brownies/", "html_title": ""}
{"title": "I should buy some cheese . . .", "selftext": "", "url": "http://imgur.com/UiUOs1F", "created_utc": 1408010594.0, "score": 6, "author": "DocCalculus", "num_comments": 0, "permalink": "/r/FoodPornGifs/comments/2dixlq/i_should_buy_some_cheese/", "html_title": ""}
{"title": "What kind of pasta do you like?", "selftext": "", "url": "https://i.redd.it/mrnrrzjeeia51.jpg", "created_utc": 1594595771.0, "score": 5, "author": "Giselle2501", "num_comments": 0, "permalink": "/r/FoodPornGifs/comments/hq48j0/what_kind_of_pasta_do_you_like/", "html_title": ""}
{"title": "My goodness, my Guinness (shamelessly stolen from /u/BigMurph26)!", "selftext": "", "url": "http://i.imgur.com/j5V01xY.gif", "created_utc": 1416880071.0, "score": 4, "author": "DocCalculus", "num_comments": 0, "permalink": "/r/FoodPornGifs/comments/2nbqvz/my_goodness_my_guinness_shamelessly_stolen_from/", "html_title": ""}
{"title": "Bacon explosion! [OS] huff post", "selftext": "", "url": "http://images.huffingtonpost.com/2014-04-17-70ZtQRq.gif", "created_utc": 1413370931.0, "score": 4, "author": "theactualstephers", "num_comments": 0, "permalink": "/r/FoodPornGifs/comments/2jb2p4/bacon_explosion_os_huff_post/", "html_title": ""}
{"title": "Manufacturing of a summer roll (2nd)", "selftext": "", "url": "https://v.redd.it/j8sytb7zsal41", "created_utc": 1583610801.0, "score": 3, "author": "vuzavuza", "num_comments": 0, "permalink": "/r/FoodPornGifs/comments/ff0gp0/manufacturing_of_a_summer_roll_2nd/", "html_title": "Reddit - The heart of the internet"}
{"title": "Stirring warm pasta.", "selftext": "", "url": "http://38.media.tumblr.com/9bae87fa35630812e5a67c8b0cf6dfaa/tumblr_mudhj3fM4x1rxgaoqo4_250.gif", "created_utc": 1410647146.0, "score": 3, "author": "Motha_Effin_Kitty_Yo", "num_comments": 0, "permalink": "/r/FoodPornGifs/comments/2gbnr1/stirring_warm_pasta/", "html_title": ""}
{"title": "Dicc pl\u00e4te", "selftext": "https://www.toprevenuegate.com/b7mwnv28?key=6891d2c5390d0e38ee0d141c3bb29834", "url": "https://v.redd.it/shg6ff00rizb1", "created_utc": 1699621388.0, "score": 2, "author": "realcoldirtybastard", "num_comments": 0, "permalink": "/r/FoodPornGifs/comments/17s3k4l/dicc_pl\u00e4te/", "html_title": "Reddit - The heart of the internet"}
{"title": "Joels bullar", "selftext": "", "url": "https://i.redd.it/u86puvtz0gv91.gif", "created_utc": 1666481980.0, "score": 2, "author": "Turbulent-Release676", "num_comments": 0, "permalink": "/r/FoodPornGifs/comments/yb260f/joels_bullar/", "html_title": ""}
{"title": "Delectable dogs", "selftext": "", "url": "https://youtube.com/shorts/oLhGcHTrdSI?feature=share", "created_utc": 1647639578.0, "score": 2, "author": "Sol_Neutralguy", "num_comments": 1, "permalink": "/r/FoodPornGifs/comments/thfvhp/delectable_dogs/", "html_title": "- YouTube"}
{"title": "I Don't Know If This Qualifies - Masterchef Jr. with Gordan Ramsay", "selftext": "", "url": "https://media.giphy.com/media/npVmSqhvx9dYs/giphy.gif", "created_utc": 1493520199.0, "score": 2, "author": "food_food_food", "num_comments": 1, "permalink": "/r/FoodPornGifs/comments/68danx/i_dont_know_if_this_qualifies_masterchef_jr_with/", "html_title": ""}
{"title": "Satisfy Your Cravings for Indian and Persian Food in Helensburgh with Koolba To Go", "selftext": "", "url": "https://www.reddit.com/gallery/17an1z0", "created_utc": 1697623368.0, "score": 1, "author": "OkraGloomy5538", "num_comments": 0, "permalink": "/r/FoodPornGifs/comments/17an1z0/satisfy_your_cravings_for_indian_and_persian_food/", "html_title": "Reddit - The heart of the internet"}
{"title": "Savor the Flavors of India and Persia with Koolba To Go in Helensburgh", "selftext": "", "url": "https://www.reddit.com/gallery/17933jz", "created_utc": 1697453069.0, "score": 1, "author": "OkraGloomy5538", "num_comments": 0, "permalink": "/r/FoodPornGifs/comments/17933jz/savor_the_flavors_of_india_and_persia_with_koolba/", "html_title": "Reddit - The heart of the internet"}
{"title": "Savor the Flavors of India with Koolba To Go - Your Local Indian Takeaway in Helensburgh", "selftext": "", "url": "https://www.reddit.com/gallery/1763yfu", "created_utc": 1697107417.0, "score": 1, "author": "OkraGloomy5538", "num_comments": 0, "permalink": "/r/FoodPornGifs/comments/1763yfu/savor_the_flavors_of_india_with_koolba_to_go_your/", "html_title": "Reddit - The heart of the internet"}
{"title": "Savor the Flavor: Uncover the Best French Italian Pizza Deals at Koolba To Go", "selftext": "", "url": "https://www.reddit.com/gallery/173r6xb", "created_utc": 1696856382.0, "score": 1, "author": "OkraGloomy5538", "num_comments": 0, "permalink": "/r/FoodPornGifs/comments/173r6xb/savor_the_flavor_uncover_the_best_french_italian/", "html_title": "Reddit - The heart of the internet"}
{"title": "Savor Authentic Flavors: Unveiling Delectable Italian Pizza Deals at Koolba To Go", "selftext": "", "url": "https://www.reddit.com/gallery/17195c5", "created_utc": 1696589451.0, "score": 1, "author": "OkraGloomy5538", "num_comments": 0, "permalink": "/r/FoodPornGifs/comments/17195c5/savor_authentic_flavors_unveiling_delectable/", "html_title": "Reddit - The heart of the internet"}
{"title": "pork recipes blog", "selftext": "", "url": "https://www.reddit.com/user/pradeepcooking/draft/c9ec6aee-9922-11ec-bea5-f240ae0b4d16", "created_utc": 1646114119.0, "score": 1, "author": "pradeepcooking", "num_comments": 0, "permalink": "/r/FoodPornGifs/comments/t40uh7/pork_recipes_blog/", "html_title": "Reddit - The heart of the internet"}
{"title": "French onion soup/crystal clear broth", "selftext": "", "url": "https://v.redd.it/68xm82cm5o081", "created_utc": 1637378595.0, "score": 1, "author": "gettincheffywithit", "num_comments": 0, "permalink": "/r/FoodPornGifs/comments/qxwmve/french_onion_soupcrystal_clear_broth/", "html_title": "Reddit - The heart of the internet"}
{"title": "What kind of pasta do you like?", "selftext": "", "url": "https://i.redd.it/78z46pobeia51.jpg", "created_utc": 1594595745.0, "score": 1, "author": "Giselle2501", "num_comments": 0, "permalink": "/r/FoodPornGifs/comments/hq489o/what_kind_of_pasta_do_you_like/", "html_title": ""}
{"title": "Moms home made zucchini bread. Still warm.... and moist.", "selftext": "", "url": "https://v.redd.it/gr1wy6dpmsj11", "created_utc": 1535880314.0, "score": 1, "author": "jimmythecow", "num_comments": 1, "permalink": "/r/FoodPornGifs/comments/9cavs4/moms_home_made_zucchini_bread_still_warm_and_moist/", "html_title": "Reddit - The heart of the internet"}
{"title": "Savor Authentic Flavors: Unveiling Delectable Italian Pizza Deals at Koolba To Go", "selftext": "", "url": "https://i.redd.it/toqb1r39bksb1.jpg", "created_utc": 1696589371.0, "score": 0, "author": "OkraGloomy5538", "num_comments": 0, "permalink": "/r/FoodPornGifs/comments/17194es/savor_authentic_flavors_unveiling_delectable/", "html_title": ""}
{"title": "pork recipes", "selftext": "", "url": "https://www.reddit.com/user/pradeepcooking/draft/c9ec6aee-9922-11ec-bea5-f240ae0b4d16", "created_utc": 1646114065.0, "score": 0, "author": "pradeepcooking", "num_comments": 0, "permalink": "/r/FoodPornGifs/comments/t40tvz/pork_recipes/", "html_title": "Reddit - The heart of the internet"}
{"title": "C\u00e1c m\u00f3n \u0103n s\u00e1ng ngon \u1edf S\u00e0i G\u00f2n \u0103n ho\u00e0i kh\u00f4ng ch\u00e1n", "selftext": "", "url": "https://jamja.vn/blog/cac-mon-an-sang-ngon-o-sai-gon.html", "created_utc": 1532588911.0, "score": 0, "author": "ledong135", "num_comments": 0, "permalink": "/r/FoodPornGifs/comments/920242/c\u00e1c_m\u00f3n_\u0103n_s\u00e1ng_ngon_\u1edf_s\u00e0i_g\u00f2n_\u0103n_ho\u00e0i_kh\u00f4ng_ch\u00e1n/", "html_title": ""}
{"title": "Dicc pl\u00e4te", "selftext": "https://www.toprevenuegate.com/b7mwnv28?key=6891d2c5390d0e38ee0d141c3bb29834", "url": "https://v.redd.it/shg6ff00rizb1", "created_utc": 1699621388.0, "score": 2, "author": "realcoldirtybastard", "num_comments": 0, "permalink": "/r/FoodPornGifs/comments/17s3k4l/dicc_pl\u00e4te/", "html_title": "Reddit - The heart of the internet"}
{"title": "Satisfy Your Cravings for Indian and Persian Food in Helensburgh with Koolba To Go", "selftext": "", "url": "https://www.reddit.com/gallery/17an1z0", "created_utc": 1697623368.0, "score": 1, "author": "OkraGloomy5538", "num_comments": 0, "permalink": "/r/FoodPornGifs/comments/17an1z0/satisfy_your_cravings_for_indian_and_persian_food/", "html_title": "Reddit - The heart of the internet"}
{"title": "Savor the Flavors of India and Persia with Koolba To Go in Helensburgh", "selftext": "", "url": "https://www.reddit.com/gallery/17933jz", "created_utc": 1697453069.0, "score": 1, "author": "OkraGloomy5538", "num_comments": 0, "permalink": "/r/FoodPornGifs/comments/17933jz/savor_the_flavors_of_india_and_persia_with_koolba/", "html_title": "Reddit - The heart of the internet"}
{"title": "Savor the Flavors of India with Koolba To Go - Your Local Indian Takeaway in Helensburgh", "selftext": "", "url": "https://www.reddit.com/gallery/1763yfu", "created_utc": 1697107417.0, "score": 1, "author": "OkraGloomy5538", "num_comments": 0, "permalink": "/r/FoodPornGifs/comments/1763yfu/savor_the_flavors_of_india_with_koolba_to_go_your/", "html_title": "Reddit - The heart of the internet"}
{"title": "Savor the Flavor: Uncover the Best French Italian Pizza Deals at Koolba To Go", "selftext": "", "url": "https://www.reddit.com/gallery/173r6xb", "created_utc": 1696856382.0, "score": 1, "author": "OkraGloomy5538", "num_comments": 0, "permalink": "/r/FoodPornGifs/comments/173r6xb/savor_the_flavor_uncover_the_best_french_italian/", "html_title": "Reddit - The heart of the internet"}
{"title": "Savor Authentic Flavors: Unveiling Delectable Italian Pizza Deals at Koolba To Go", "selftext": "", "url": "https://www.reddit.com/gallery/17195c5", "created_utc": 1696589451.0, "score": 1, "author": "OkraGloomy5538", "num_comments": 0, "permalink": "/r/FoodPornGifs/comments/17195c5/savor_authentic_flavors_unveiling_delectable/", "html_title": "Reddit - The heart of the internet"}
{"title": "Savor Authentic Flavors: Unveiling Delectable Italian Pizza Deals at Koolba To Go", "selftext": "", "url": "https://i.redd.it/toqb1r39bksb1.jpg", "created_utc": 1696589371.0, "score": 0, "author": "OkraGloomy5538", "num_comments": 0, "permalink": "/r/FoodPornGifs/comments/17194es/savor_authentic_flavors_unveiling_delectable/", "html_title": ""}
{"title": "Blue food porn \ud83d\udc99", "selftext": "", "url": "https://v.redd.it/pmvn73d7emw91", "created_utc": 1666994911.0, "score": 6, "author": "Stinkylilsockies", "num_comments": 0, "permalink": "/r/FoodPornGifs/comments/yg21gd/blue_food_porn/", "html_title": "Reddit - The heart of the internet"}
{"title": "Joels bullar", "selftext": "", "url": "https://i.redd.it/u86puvtz0gv91.gif", "created_utc": 1666481980.0, "score": 2, "author": "Turbulent-Release676", "num_comments": 0, "permalink": "/r/FoodPornGifs/comments/yb260f/joels_bullar/", "html_title": ""}
{"title": "Delectable dogs", "selftext": "", "url": "https://youtube.com/shorts/oLhGcHTrdSI?feature=share", "created_utc": 1647639578.0, "score": 2, "author": "Sol_Neutralguy", "num_comments": 1, "permalink": "/r/FoodPornGifs/comments/thfvhp/delectable_dogs/", "html_title": "- YouTube"}
{"title": "pork recipes blog", "selftext": "", "url": "https://www.reddit.com/user/pradeepcooking/draft/c9ec6aee-9922-11ec-bea5-f240ae0b4d16", "created_utc": 1646114119.0, "score": 1, "author": "pradeepcooking", "num_comments": 0, "permalink": "/r/FoodPornGifs/comments/t40uh7/pork_recipes_blog/", "html_title": "Reddit - The heart of the internet"}
{"title": "pork recipes", "selftext": "", "url": "https://www.reddit.com/user/pradeepcooking/draft/c9ec6aee-9922-11ec-bea5-f240ae0b4d16", "created_utc": 1646114065.0, "score": 0, "author": "pradeepcooking", "num_comments": 0, "permalink": "/r/FoodPornGifs/comments/t40tvz/pork_recipes/", "html_title": "Reddit - The heart of the internet"}
{"title": "French onion soup/crystal clear broth", "selftext": "", "url": "https://v.redd.it/68xm82cm5o081", "created_utc": 1637378595.0, "score": 1, "author": "gettincheffywithit", "num_comments": 0, "permalink": "/r/FoodPornGifs/comments/qxwmve/french_onion_soupcrystal_clear_broth/", "html_title": "Reddit - The heart of the internet"}
{"title": "Focaccia Charcuterie Board", "selftext": "", "url": "https://v.redd.it/jjf1u4pf0jl71", "created_utc": 1630778576.0, "score": 25, "author": "CableStoned", "num_comments": 0, "permalink": "/r/FoodPornGifs/comments/phwflo/focaccia_charcuterie_board/", "html_title": "Reddit - The heart of the internet"}
{"title": "Dessert from \"Chop\" at the Venetian", "selftext": "", "url": "https://v.redd.it/h3ocjbfj3or61", "created_utc": 1617764735.0, "score": 19, "author": "Yubenbroken", "num_comments": 1, "permalink": "/r/FoodPornGifs/comments/mlstg8/dessert_from_chop_at_the_venetian/", "html_title": "Reddit - The heart of the internet"}
{"title": "Homemade Boba milk tea", "selftext": "", "url": "https://v.redd.it/wporcujmeo561", "created_utc": 1608179784.0, "score": 11, "author": "sturdybison74", "num_comments": 0, "permalink": "/r/FoodPornGifs/comments/keqf32/homemade_boba_milk_tea/", "html_title": "Reddit - The heart of the internet"}
{"title": "Steak&Eggs", "selftext": "", "url": "https://v.redd.it/8yswxaou7h561", "created_utc": 1608092769.0, "score": 11, "author": "Whitebread_92", "num_comments": 0, "permalink": "/r/FoodPornGifs/comments/ke28ir/steakeggs/", "html_title": "Reddit - The heart of the internet"}
{"title": "its sushi time - art by me", "selftext": "", "url": "https://i.redd.it/qycimuhr29c51.gif", "created_utc": 1595354599.0, "score": 11, "author": "mangadrawing123", "num_comments": 1, "permalink": "/r/FoodPornGifs/comments/hvcd4b/its_sushi_time_art_by_me/", "html_title": ""}
{"title": "Waffle Porn. Crispy on the outside, Fluffy on the inside :) - Recipe in comment.", "selftext": "", "url": "https://gfycat.com/wideeyedamazinghectorsdolphin", "created_utc": 1594618695.0, "score": 12, "author": "mahcyen", "num_comments": 1, "permalink": "/r/FoodPornGifs/comments/hq9o0g/waffle_porn_crispy_on_the_outside_fluffy_on_the/", "html_title": ""}
{"title": "What kind of pasta do you like?", "selftext": "", "url": "https://i.redd.it/mrnrrzjeeia51.jpg", "created_utc": 1594595771.0, "score": 5, "author": "Giselle2501", "num_comments": 0, "permalink": "/r/FoodPornGifs/comments/hq48j0/what_kind_of_pasta_do_you_like/", "html_title": ""}
{"title": "What kind of pasta do you like?", "selftext": "", "url": "https://i.redd.it/78z46pobeia51.jpg", "created_utc": 1594595745.0, "score": 1, "author": "Giselle2501", "num_comments": 0, "permalink": "/r/FoodPornGifs/comments/hq489o/what_kind_of_pasta_do_you_like/", "html_title": ""}
{"title": "Tomahawk steak on chimney grill", "selftext": "", "url": "https://v.redd.it/2hls88x1gbz41", "created_utc": 1589717294.0, "score": 11, "author": "wanton85", "num_comments": 1, "permalink": "/r/FoodPornGifs/comments/glebkw/tomahawk_steak_on_chimney_grill/", "html_title": "Reddit - The heart of the internet"}
{"title": "Ignore my dirty oven please", "selftext": "", "url": "https://v.redd.it/eoyrg8wt23v41", "created_utc": 1587872560.0, "score": 22, "author": "KittyNouveau", "num_comments": 1, "permalink": "/r/FoodPornGifs/comments/g87ges/ignore_my_dirty_oven_please/", "html_title": "Reddit - The heart of the internet"}
{"title": "Egg porn over a open faced steak sandwich.", "selftext": "", "url": "https://v.redd.it/g7ml724hyes41", "created_utc": 1586708892.0, "score": 15, "author": "1578W", "num_comments": 0, "permalink": "/r/FoodPornGifs/comments/fzzrcz/egg_porn_over_a_open_faced_steak_sandwich/", "html_title": "Reddit - The heart of the internet"}
{"title": "Manufacturing of a summer roll (2nd)", "selftext": "", "url": "https://v.redd.it/j8sytb7zsal41", "created_utc": 1583610801.0, "score": 3, "author": "vuzavuza", "num_comments": 0, "permalink": "/r/FoodPornGifs/comments/ff0gp0/manufacturing_of_a_summer_roll_2nd/", "html_title": "Reddit - The heart of the internet"}
{"title": "Unacceptable", "selftext": "", "url": "https://i.redd.it/3acuole8bwx31.jpg", "created_utc": 1573407647.0, "score": 19, "author": "howthefuge6", "num_comments": 1, "permalink": "/r/FoodPornGifs/comments/dueil1/unacceptable/", "html_title": ""}
{"title": "Baileys Ganache on sweet potato brownies", "selftext": "", "url": "https://gfycat.com/tidypracticalheron", "created_utc": 1563530653.0, "score": 6, "author": "pixxelzombie", "num_comments": 1, "permalink": "/r/FoodPornGifs/comments/cf5oyf/baileys_ganache_on_sweet_potato_brownies/", "html_title": ""}
{"title": "Homemade", "selftext": "", "url": "https://v.redd.it/pgxxt04etip21", "created_utc": 1554066986.0, "score": 16, "author": "None", "num_comments": 0, "permalink": "/r/FoodPornGifs/comments/b7svo1/homemade/", "html_title": "Reddit - The heart of the internet"}
{"title": "Moms home made zucchini bread. Still warm.... and moist.", "selftext": "", "url": "https://v.redd.it/gr1wy6dpmsj11", "created_utc": 1535880314.0, "score": 1, "author": "jimmythecow", "num_comments": 1, "permalink": "/r/FoodPornGifs/comments/9cavs4/moms_home_made_zucchini_bread_still_warm_and_moist/", "html_title": "Reddit - The heart of the internet"}
{"title": "C\u00e1c m\u00f3n \u0103n s\u00e1ng ngon \u1edf S\u00e0i G\u00f2n \u0103n ho\u00e0i kh\u00f4ng ch\u00e1n", "selftext": "", "url": "https://jamja.vn/blog/cac-mon-an-sang-ngon-o-sai-gon.html", "created_utc": 1532588911.0, "score": 0, "author": "ledong135", "num_comments": 0, "permalink": "/r/FoodPornGifs/comments/920242/c\u00e1c_m\u00f3n_\u0103n_s\u00e1ng_ngon_\u1edf_s\u00e0i_g\u00f2n_\u0103n_ho\u00e0i_kh\u00f4ng_ch\u00e1n/", "html_title": ""}
{"title": "I Don't Know If This Qualifies - Masterchef Jr. with Gordan Ramsay", "selftext": "", "url": "https://media.giphy.com/media/npVmSqhvx9dYs/giphy.gif", "created_utc": 1493520199.0, "score": 2, "author": "food_food_food", "num_comments": 1, "permalink": "/r/FoodPornGifs/comments/68danx/i_dont_know_if_this_qualifies_masterchef_jr_with/", "html_title": ""}
{"title": "Castella Sponge Cake [xpost r/oddlysatisfying]", "selftext": "", "url": "http://i.imgur.com/0J7CWZr.gifv", "created_utc": 1455678583.0, "score": 11, "author": "Hashbrown777", "num_comments": 2, "permalink": "/r/FoodPornGifs/comments/4667nc/castella_sponge_cake_xpost_roddlysatisfying/", "html_title": ""}
{"title": "Chocolate Mousse", "selftext": "", "url": "http://24.media.tumblr.com/tumblr_mdv23l2fqs1rzko2no1_500.gif", "created_utc": 1430997970.0, "score": 7, "author": "Oddslat", "num_comments": 0, "permalink": "/r/FoodPornGifs/comments/355xk4/chocolate_mousse/", "html_title": ""}
{"title": "My goodness, my Guinness (shamelessly stolen from /u/BigMurph26)!", "selftext": "", "url": "http://i.imgur.com/j5V01xY.gif", "created_utc": 1416880071.0, "score": 4, "author": "DocCalculus", "num_comments": 0, "permalink": "/r/FoodPornGifs/comments/2nbqvz/my_goodness_my_guinness_shamelessly_stolen_from/", "html_title": ""}
{"title": "Bacon explosion! [OS] huff post", "selftext": "", "url": "http://images.huffingtonpost.com/2014-04-17-70ZtQRq.gif", "created_utc": 1413370931.0, "score": 3, "author": "theactualstephers", "num_comments": 0, "permalink": "/r/FoodPornGifs/comments/2jb2p4/bacon_explosion_os_huff_post/", "html_title": ""}
{"title": "Tearing into a pizza.", "selftext": "", "url": "http://i.imgur.com/7siGit8.gif", "created_utc": 1410646525.0, "score": 9, "author": "Motha_Effin_Kitty_Yo", "num_comments": 2, "permalink": "/r/FoodPornGifs/comments/2gbmsq/tearing_into_a_pizza/", "html_title": ""}
{"title": "Stirring warm pasta.", "selftext": "", "url": "http://38.media.tumblr.com/9bae87fa35630812e5a67c8b0cf6dfaa/tumblr_mudhj3fM4x1rxgaoqo4_250.gif", "created_utc": 1410647146.0, "score": 3, "author": "Motha_Effin_Kitty_Yo", "num_comments": 0, "permalink": "/r/FoodPornGifs/comments/2gbnr1/stirring_warm_pasta/", "html_title": ""}
{"title": "I should buy some cheese . . .", "selftext": "", "url": "http://imgur.com/UiUOs1F", "created_utc": 1408010594.0, "score": 7, "author": "DocCalculus", "num_comments": 0, "permalink": "/r/FoodPornGifs/comments/2dixlq/i_should_buy_some_cheese/", "html_title": ""}
{"title": "A Delectable Dessert.", "selftext": "", "url": "http://gfycat.com/CloseWellinformedChimpanzee", "created_utc": 1407982323.0, "score": 11, "author": "Motha_Effin_Kitty_Yo", "num_comments": 0, "permalink": "/r/FoodPornGifs/comments/2dhzhw/a_delectable_dessert/", "html_title": ""}
{"title": "Pizza! I don't even eat cheese pizza, but damn, this makes me want to.", "selftext": "", "url": "http://imgur.com/xRMDCkV", "created_utc": 1407824820.0, "score": 8, "author": "asifsys23", "num_comments": 0, "permalink": "/r/FoodPornGifs/comments/2dbb1s/pizza_i_dont_even_eat_cheese_pizza_but_damn_this/", "html_title": ""}
{"title": "Filet in a frying pan", "selftext": "", "url": "http://i.imgur.com/tZ8gZxn.gif", "created_utc": 1401472548.0, "score": 15, "author": "holdenwook", "num_comments": 1, "permalink": "/r/FoodPornGifs/comments/26w4mm/filet_in_a_frying_pan/", "html_title": ""}
{"title": "Dicc pl\u00e4te", "selftext": "https://www.toprevenuegate.com/b7mwnv28?key=6891d2c5390d0e38ee0d141c3bb29834", "url": "https://v.redd.it/shg6ff00rizb1", "created_utc": 1699621388.0, "score": 2, "author": "realcoldirtybastard", "num_comments": 0, "permalink": "/r/FoodPornGifs/comments/17s3k4l/dicc_pl\u00e4te/", "html_title": "Reddit - The heart of the internet"}
{"title": "Satisfy Your Cravings for Indian and Persian Food in Helensburgh with Koolba To Go", "selftext": "", "url": "https://www.reddit.com/gallery/17an1z0", "created_utc": 1697623368.0, "score": 1, "author": "OkraGloomy5538", "num_comments": 0, "permalink": "/r/FoodPornGifs/comments/17an1z0/satisfy_your_cravings_for_indian_and_persian_food/", "html_title": "Reddit - The heart of the internet"}
{"title": "Savor the Flavors of India and Persia with Koolba To Go in Helensburgh", "selftext": "", "url": "https://www.reddit.com/gallery/17933jz", "created_utc": 1697453069.0, "score": 1, "author": "OkraGloomy5538", "num_comments": 0, "permalink": "/r/FoodPornGifs/comments/17933jz/savor_the_flavors_of_india_and_persia_with_koolba/", "html_title": "Reddit - The heart of the internet"}
{"title": "Savor the Flavors of India with Koolba To Go - Your Local Indian Takeaway in Helensburgh", "selftext": "", "url": "https://www.reddit.com/gallery/1763yfu", "created_utc": 1697107417.0, "score": 1, "author": "OkraGloomy5538", "num_comments": 0, "permalink": "/r/FoodPornGifs/comments/1763yfu/savor_the_flavors_of_india_with_koolba_to_go_your/", "html_title": "Reddit - The heart of the internet"}
{"title": "Savor the Flavor: Uncover the Best French Italian Pizza Deals at Koolba To Go", "selftext": "", "url": "https://www.reddit.com/gallery/173r6xb", "created_utc": 1696856382.0, "score": 1, "author": "OkraGloomy5538", "num_comments": 0, "permalink": "/r/FoodPornGifs/comments/173r6xb/savor_the_flavor_uncover_the_best_french_italian/", "html_title": "Reddit - The heart of the internet"}
{"title": "Savor Authentic Flavors: Unveiling Delectable Italian Pizza Deals at Koolba To Go", "selftext": "", "url": "https://www.reddit.com/gallery/17195c5", "created_utc": 1696589451.0, "score": 1, "author": "OkraGloomy5538", "num_comments": 0, "permalink": "/r/FoodPornGifs/comments/17195c5/savor_authentic_flavors_unveiling_delectable/", "html_title": "Reddit - The heart of the internet"}
{"title": "Savor Authentic Flavors: Unveiling Delectable Italian Pizza Deals at Koolba To Go", "selftext": "", "url": "https://i.redd.it/toqb1r39bksb1.jpg", "created_utc": 1696589371.0, "score": 0, "author": "OkraGloomy5538", "num_comments": 0, "permalink": "/r/FoodPornGifs/comments/17194es/savor_authentic_flavors_unveiling_delectable/", "html_title": ""}
{"title": "Blue food porn \ud83d\udc99", "selftext": "", "url": "https://v.redd.it/pmvn73d7emw91", "created_utc": 1666994911.0, "score": 7, "author": "Stinkylilsockies", "num_comments": 0, "permalink": "/r/FoodPornGifs/comments/yg21gd/blue_food_porn/", "html_title": "Reddit - The heart of the internet"}
{"title": "Joels bullar", "selftext": "", "url": "https://i.redd.it/u86puvtz0gv91.gif", "created_utc": 1666481980.0, "score": 2, "author": "Turbulent-Release676", "num_comments": 0, "permalink": "/r/FoodPornGifs/comments/yb260f/joels_bullar/", "html_title": ""}
{"title": "Delectable dogs", "selftext": "", "url": "https://youtube.com/shorts/oLhGcHTrdSI?feature=share", "created_utc": 1647639578.0, "score": 2, "author": "Sol_Neutralguy", "num_comments": 1, "permalink": "/r/FoodPornGifs/comments/thfvhp/delectable_dogs/", "html_title": "- YouTube"}
{"title": "pork recipes blog", "selftext": "", "url": "https://www.reddit.com/user/pradeepcooking/draft/c9ec6aee-9922-11ec-bea5-f240ae0b4d16", "created_utc": 1646114119.0, "score": 1, "author": "pradeepcooking", "num_comments": 0, "permalink": "/r/FoodPornGifs/comments/t40uh7/pork_recipes_blog/", "html_title": "Reddit - The heart of the internet"}
{"title": "pork recipes", "selftext": "", "url": "https://www.reddit.com/user/pradeepcooking/draft/c9ec6aee-9922-11ec-bea5-f240ae0b4d16", "created_utc": 1646114065.0, "score": 0, "author": "pradeepcooking", "num_comments": 0, "permalink": "/r/FoodPornGifs/comments/t40tvz/pork_recipes/", "html_title": "Reddit - The heart of the internet"}
{"title": "French onion soup/crystal clear broth", "selftext": "", "url": "https://v.redd.it/68xm82cm5o081", "created_utc": 1637378595.0, "score": 1, "author": "gettincheffywithit", "num_comments": 0, "permalink": "/r/FoodPornGifs/comments/qxwmve/french_onion_soupcrystal_clear_broth/", "html_title": "Reddit - The heart of the internet"}
{"title": "Focaccia Charcuterie Board", "selftext": "", "url": "https://v.redd.it/jjf1u4pf0jl71", "created_utc": 1630778576.0, "score": 25, "author": "CableStoned", "num_comments": 0, "permalink": "/r/FoodPornGifs/comments/phwflo/focaccia_charcuterie_board/", "html_title": "Reddit - The heart of the internet"}
{"title": "Dessert from \"Chop\" at the Venetian", "selftext": "", "url": "https://v.redd.it/h3ocjbfj3or61", "created_utc": 1617764735.0, "score": 20, "author": "Yubenbroken", "num_comments": 1, "permalink": "/r/FoodPornGifs/comments/mlstg8/dessert_from_chop_at_the_venetian/", "html_title": "Reddit - The heart of the internet"}
{"title": "Homemade Boba milk tea", "selftext": "", "url": "https://v.redd.it/wporcujmeo561", "created_utc": 1608179784.0, "score": 11, "author": "sturdybison74", "num_comments": 0, "permalink": "/r/FoodPornGifs/comments/keqf32/homemade_boba_milk_tea/", "html_title": "Reddit - The heart of the internet"}
{"title": "Steak&Eggs", "selftext": "", "url": "https://v.redd.it/8yswxaou7h561", "created_utc": 1608092769.0, "score": 11, "author": "Whitebread_92", "num_comments": 0, "permalink": "/r/FoodPornGifs/comments/ke28ir/steakeggs/", "html_title": "Reddit - The heart of the internet"}
{"title": "its sushi time - art by me", "selftext": "", "url": "https://i.redd.it/qycimuhr29c51.gif", "created_utc": 1595354599.0, "score": 9, "author": "mangadrawing123", "num_comments": 1, "permalink": "/r/FoodPornGifs/comments/hvcd4b/its_sushi_time_art_by_me/", "html_title": ""}
{"title": "Waffle Porn. Crispy on the outside, Fluffy on the inside :) - Recipe in comment.", "selftext": "", "url": "https://gfycat.com/wideeyedamazinghectorsdolphin", "created_utc": 1594618695.0, "score": 13, "author": "mahcyen", "num_comments": 1, "permalink": "/r/FoodPornGifs/comments/hq9o0g/waffle_porn_crispy_on_the_outside_fluffy_on_the/", "html_title": ""}
{"title": "What kind of pasta do you like?", "selftext": "", "url": "https://i.redd.it/mrnrrzjeeia51.jpg", "created_utc": 1594595771.0, "score": 5, "author": "Giselle2501", "num_comments": 0, "permalink": "/r/FoodPornGifs/comments/hq48j0/what_kind_of_pasta_do_you_like/", "html_title": ""}
{"title": "What kind of pasta do you like?", "selftext": "", "url": "https://i.redd.it/78z46pobeia51.jpg", "created_utc": 1594595745.0, "score": 1, "author": "Giselle2501", "num_comments": 0, "permalink": "/r/FoodPornGifs/comments/hq489o/what_kind_of_pasta_do_you_like/", "html_title": ""}
{"title": "Tomahawk steak on chimney grill", "selftext": "", "url": "https://v.redd.it/2hls88x1gbz41", "created_utc": 1589717294.0, "score": 11, "author": "wanton85", "num_comments": 1, "permalink": "/r/FoodPornGifs/comments/glebkw/tomahawk_steak_on_chimney_grill/", "html_title": "Reddit - The heart of the internet"}
{"title": "Ignore my dirty oven please", "selftext": "", "url": "https://v.redd.it/eoyrg8wt23v41", "created_utc": 1587872560.0, "score": 22, "author": "KittyNouveau", "num_comments": 1, "permalink": "/r/FoodPornGifs/comments/g87ges/ignore_my_dirty_oven_please/", "html_title": "Reddit - The heart of the internet"}
{"title": "Egg porn over a open faced steak sandwich.", "selftext": "", "url": "https://v.redd.it/g7ml724hyes41", "created_utc": 1586708892.0, "score": 15, "author": "1578W", "num_comments": 0, "permalink": "/r/FoodPornGifs/comments/fzzrcz/egg_porn_over_a_open_faced_steak_sandwich/", "html_title": "Reddit - The heart of the internet"}
{"title": "Manufacturing of a summer roll (2nd)", "selftext": "", "url": "https://v.redd.it/j8sytb7zsal41", "created_utc": 1583610801.0, "score": 3, "author": "vuzavuza", "num_comments": 0, "permalink": "/r/FoodPornGifs/comments/ff0gp0/manufacturing_of_a_summer_roll_2nd/", "html_title": "Reddit - The heart of the internet"}
{"title": "Unacceptable", "selftext": "", "url": "https://i.redd.it/3acuole8bwx31.jpg", "created_utc": 1573407647.0, "score": 20, "author": "howthefuge6", "num_comments": 1, "permalink": "/r/FoodPornGifs/comments/dueil1/unacceptable/", "html_title": ""}
{"title": "Baileys Ganache on sweet potato brownies", "selftext": "", "url": "https://gfycat.com/tidypracticalheron", "created_utc": 1563530653.0, "score": 7, "author": "pixxelzombie", "num_comments": 1, "permalink": "/r/FoodPornGifs/comments/cf5oyf/baileys_ganache_on_sweet_potato_brownies/", "html_title": ""}
{"title": "Homemade", "selftext": "", "url": "https://v.redd.it/pgxxt04etip21", "created_utc": 1554066986.0, "score": 16, "author": "None", "num_comments": 0, "permalink": "/r/FoodPornGifs/comments/b7svo1/homemade/", "html_title": "Reddit - The heart of the internet"}
{"title": "Moms home made zucchini bread. Still warm.... and moist.", "selftext": "", "url": "https://v.redd.it/gr1wy6dpmsj11", "created_utc": 1535880314.0, "score": 1, "author": "jimmythecow", "num_comments": 1, "permalink": "/r/FoodPornGifs/comments/9cavs4/moms_home_made_zucchini_bread_still_warm_and_moist/", "html_title": "Reddit - The heart of the internet"}
{"title": "C\u00e1c m\u00f3n \u0103n s\u00e1ng ngon \u1edf S\u00e0i G\u00f2n \u0103n ho\u00e0i kh\u00f4ng ch\u00e1n", "selftext": "", "url": "https://jamja.vn/blog/cac-mon-an-sang-ngon-o-sai-gon.html", "created_utc": 1532588911.0, "score": 0, "author": "ledong135", "num_comments": 0, "permalink": "/r/FoodPornGifs/comments/920242/c\u00e1c_m\u00f3n_\u0103n_s\u00e1ng_ngon_\u1edf_s\u00e0i_g\u00f2n_\u0103n_ho\u00e0i_kh\u00f4ng_ch\u00e1n/", "html_title": ""}
{"title": "I Don't Know If This Qualifies - Masterchef Jr. with Gordan Ramsay", "selftext": "", "url": "https://media.giphy.com/media/npVmSqhvx9dYs/giphy.gif", "created_utc": 1493520199.0, "score": 2, "author": "food_food_food", "num_comments": 1, "permalink": "/r/FoodPornGifs/comments/68danx/i_dont_know_if_this_qualifies_masterchef_jr_with/", "html_title": ""}
{"title": "Castella Sponge Cake [xpost r/oddlysatisfying]", "selftext": "", "url": "http://i.imgur.com/0J7CWZr.gifv", "created_utc": 1455678583.0, "score": 12, "author": "Hashbrown777", "num_comments": 2, "permalink": "/r/FoodPornGifs/comments/4667nc/castella_sponge_cake_xpost_roddlysatisfying/", "html_title": ""}
{"title": "Chocolate Mousse", "selftext": "", "url": "http://24.media.tumblr.com/tumblr_mdv23l2fqs1rzko2no1_500.gif", "created_utc": 1430997970.0, "score": 9, "author": "Oddslat", "num_comments": 0, "permalink": "/r/FoodPornGifs/comments/355xk4/chocolate_mousse/", "html_title": ""}
{"title": "My goodness, my Guinness (shamelessly stolen from /u/BigMurph26)!", "selftext": "", "url": "http://i.imgur.com/j5V01xY.gif", "created_utc": 1416880071.0, "score": 4, "author": "DocCalculus", "num_comments": 0, "permalink": "/r/FoodPornGifs/comments/2nbqvz/my_goodness_my_guinness_shamelessly_stolen_from/", "html_title": ""}
{"title": "Bacon explosion! [OS] huff post", "selftext": "", "url": "http://images.huffingtonpost.com/2014-04-17-70ZtQRq.gif", "created_utc": 1413370931.0, "score": 3, "author": "theactualstephers", "num_comments": 0, "permalink": "/r/FoodPornGifs/comments/2jb2p4/bacon_explosion_os_huff_post/", "html_title": ""}
{"title": "Stirring warm pasta.", "selftext": "", "url": "http://38.media.tumblr.com/9bae87fa35630812e5a67c8b0cf6dfaa/tumblr_mudhj3fM4x1rxgaoqo4_250.gif", "created_utc": 1410647146.0, "score": 3, "author": "Motha_Effin_Kitty_Yo", "num_comments": 0, "permalink": "/r/FoodPornGifs/comments/2gbnr1/stirring_warm_pasta/", "html_title": ""}
{"title": "Tearing into a pizza.", "selftext": "", "url": "http://i.imgur.com/7siGit8.gif", "created_utc": 1410646525.0, "score": 8, "author": "Motha_Effin_Kitty_Yo", "num_comments": 2, "permalink": "/r/FoodPornGifs/comments/2gbmsq/tearing_into_a_pizza/", "html_title": ""}
{"title": "I should buy some cheese . . .", "selftext": "", "url": "http://imgur.com/UiUOs1F", "created_utc": 1408010594.0, "score": 6, "author": "DocCalculus", "num_comments": 0, "permalink": "/r/FoodPornGifs/comments/2dixlq/i_should_buy_some_cheese/", "html_title": ""}
{"title": "A Delectable Dessert.", "selftext": "", "url": "http://gfycat.com/CloseWellinformedChimpanzee", "created_utc": 1407982323.0, "score": 10, "author": "Motha_Effin_Kitty_Yo", "num_comments": 0, "permalink": "/r/FoodPornGifs/comments/2dhzhw/a_delectable_dessert/", "html_title": ""}
{"title": "Pizza! I don't even eat cheese pizza, but damn, this makes me want to.", "selftext": "", "url": "http://imgur.com/xRMDCkV", "created_utc": 1407824820.0, "score": 9, "author": "asifsys23", "num_comments": 0, "permalink": "/r/FoodPornGifs/comments/2dbb1s/pizza_i_dont_even_eat_cheese_pizza_but_damn_this/", "html_title": ""}
{"title": "Filet in a frying pan", "selftext": "", "url": "http://i.imgur.com/tZ8gZxn.gif", "created_utc": 1401472548.0, "score": 18, "author": "holdenwook", "num_comments": 1, "permalink": "/r/FoodPornGifs/comments/26w4mm/filet_in_a_frying_pan/", "html_title": ""}
